LICENSE.md
MANIFEST.in
README.md
dynamic_extras_require.txt
dynamic_install_requires.txt
quicklib_incorporated.v2.5.zip
quicklib_setup_from_yml.py
epic/pandas/__init__.py
epic/pandas/__version__.py
epic/pandas/algorithm.py
epic/pandas/create.py
epic/pandas/networkx.py
epic/pandas/numpy.py
epic/pandas/parallel.py
epic/pandas/sparse.py
epic/pandas/utils.py
epic/pandas/matplotlib/__init__.py
epic/pandas/matplotlib/colors.py
epic/pandas/matplotlib/format.py
epic/pandas/matplotlib/plot.py
epic/pandas/matplotlib/utils.py
epic/pandas/tests/__init__.py
epic/pandas/tests/test_numpy.py
epic/pandas/tests/test_utils.py
epic_pandas.egg-info/PKG-INFO
epic_pandas.egg-info/SOURCES.txt
epic_pandas.egg-info/dependency_links.txt
epic_pandas.egg-info/requires.txt
epic_pandas.egg-info/top_level.txt