Metadata-Version: 2.1
Name: epic-pandas
Version: 1.0
Summary: Extra treats for the data-oriented
Home-page: https://github.com/Cybereason/epic-pandas
Author: Assaf Ben-David, Yonatan Perry, Uri Sternfeld
License: MIT License
Platform: UNKNOWN
Classifier: Development Status :: 4 - Beta
Classifier: Intended Audience :: Developers
Classifier: Operating System :: POSIX :: Linux
Classifier: Operating System :: MacOS :: MacOS X
Classifier: Operating System :: Microsoft :: Windows
Classifier: Programming Language :: Python :: 3 :: Only
Classifier: Programming Language :: Python :: 3.10
Requires-Python: >=3.10
License-File: LICENSE.md
